sbat/__init__.py
sbat/analysis.py
sbat/interactive_plots.py
sbat/jellyfish_analysis.py
sbat/main.py
sbat/nanopore.py
sbat/utils.py
sbat-0.0.10.dist-info/METADATA
sbat-0.0.10.dist-info/WHEEL
sbat-0.0.10.dist-info/entry_points.txt
sbat-0.0.10.dist-info/top_level.txt
sbat-0.0.10.dist-info/RECORD
