Metadata-Version: 2.1
Name: sbat
Version: 0.0.10
Summary: A tool for strand bias analysis of NGS data
Home-page: https://github.com/alex-skyslakova/strand-bias-analysis-tool
Author: Alexandra Skyslakova
Author-email: alexandra.skyslakova@gmail.com
Classifier: Programming Language :: Python :: 3.7
Classifier: License :: OSI Approved :: MIT License
Classifier: Operating System :: MacOS
Classifier: Operating System :: Unix
Requires-Python: >=3.7
Requires-Dist: Bio (==1.4.0)
Requires-Dist: bokeh (==2.4.3)
Requires-Dist: matplotlib (==3.6.1)
Requires-Dist: numpy (==1.22.3)
Requires-Dist: pandas (==1.4.2)
Requires-Dist: python-dateutil (==2.8.2)
Requires-Dist: pytz (==2022.1)
Requires-Dist: setuptools (==45.2.0)
Requires-Dist: tornado (==6.1)
